README.rst
setup.py
django_viter.egg-info/PKG-INFO
django_viter.egg-info/SOURCES.txt
django_viter.egg-info/dependency_links.txt
django_viter.egg-info/not-zip-safe
django_viter.egg-info/top_level.txt
testing/__init__.py
testing/settings.py
testing/urls.py
viter/__init__.py
viter/models.py
viter/settings.py
viter/viter.py
viter/generatorhandlers/__init__.py
viter/generatorhandlers/generatorhandlerbase.py
viter/generatorhandlers/nogeneratorhandler.py
viter/generatorhandlers/uuidgeneratorhandler.py
viter/sendmailhandlers/__init__.py
viter/sendmailhandlers/nosendmailhandler.py
viter/sendmailhandlers/plainsendmailhandler.py
viter/sendmailhandlers/sendmailhandlerbase.py
viter/storehandlers/__init__.py
viter/storehandlers/nostorehandler.py
viter/storehandlers/storehandlerbase.py
viter/storehandlers/dbstorehandler/__init__.py
viter/storehandlers/dbstorehandler/admin.py
viter/storehandlers/dbstorehandler/models.py
viter/tests/__init__.py
viter/tests/test_viter.py