Metadata-Version: 1.1
Name: django-viter
Version: 0.0.1
Summary: Invite users to your Django apps
Home-page: UNKNOWN
Author: Jesús Espino
Author-email: jespinog@gmail.com
License: UNKNOWN
Platform: UNKNOWN
Classifier: Environment :: Web Environment
Classifier: Intended Audience :: Developers
Classifier: License :: OSI Approved :: BSD License
Classifier: Operating System :: OS Independent
Classifier: Programming Language :: Python
Classifier: Framework :: Django
